MNIST_data_processor-1.0.dist-info/METADATA
MNIST_data_processor-1.0.dist-info/RECORD
MNIST_data_processor-1.0.dist-info/WHEEL
MNIST_data_processor-1.0.dist-info/top_level.txt
mnistdp/IdxFile.py
mnistdp/MNISTProcessor.py
mnistdp/__init__.py
